djangocms_katex/__init__.py
djangocms_katex/cms_plugins.py
djangocms_katex/forms.py
djangocms_katex/models.py
djangocms_katex/locale/de/LC_MESSAGES/django.po
djangocms_katex/locale/en/LC_MESSAGES/django.po
djangocms_katex/migrations/0001_initial.py
djangocms_katex/migrations/0002_alter_katex_katex_display_style.py
djangocms_katex/migrations/__init__.py
djangocms_katex/static/djangocms_katex/admin/css/preview.css
djangocms_katex/static/djangocms_katex/admin/js/preview.js
djangocms_katex/static/djangocms_katex/vendor/katex/README.md
djangocms_katex/static/djangocms_katex/vendor/katex/katex-swap.css
djangocms_katex/static/djangocms_katex/vendor/katex/katex-swap.min.css
djangocms_katex/static/djangocms_katex/vendor/katex/katex.css
djangocms_katex/static/djangocms_katex/vendor/katex/katex.js
djangocms_katex/static/djangocms_katex/vendor/katex/katex.min.css
djangocms_katex/static/djangocms_katex/vendor/katex/katex.min.js
djangocms_katex/static/djangocms_katex/vendor/katex/katex.mjs
djangocms_katex/static/djangocms_katex/vendor/katex/contrib/auto-render.js
djangocms_katex/static/djangocms_katex/vendor/katex/contrib/auto-render.min.js
djangocms_katex/static/djangocms_katex/vendor/katex/contrib/auto-render.mjs
djangocms_katex/static/djangocms_katex/vendor/katex/contrib/copy-tex.js
djangocms_katex/static/djangocms_katex/vendor/katex/contrib/copy-tex.min.js
djangocms_katex/static/djangocms_katex/vendor/katex/contrib/copy-tex.mjs
djangocms_katex/static/djangocms_katex/vendor/katex/contrib/mathtex-script-type.js
djangocms_katex/static/djangocms_katex/vendor/katex/contrib/mathtex-script-type.min.js
djangocms_katex/static/djangocms_katex/vendor/katex/contrib/mathtex-script-type.mjs
djangocms_katex/static/djangocms_katex/vendor/katex/contrib/mhchem.js
djangocms_katex/static/djangocms_katex/vendor/katex/contrib/mhchem.min.js
djangocms_katex/static/djangocms_katex/vendor/katex/contrib/mhchem.mjs
djangocms_katex/static/djangocms_katex/vendor/katex/contrib/render-a11y-string.js
djangocms_katex-1.0.1.dist-info/METADATA
djangocms_katex-1.0.1.dist-info/WHEEL
djangocms_katex-1.0.1.dist-info/licenses/LICENSE
djangocms_katex-1.0.1.dist-info/RECORD
