Metadata-Version: 2.4
Name: djangocms-katex
Version: 1.0.1
Summary: Provides plugin to render formulae in django CMS
Project-URL: Homepage, https://github.com/fsbraun/djangocms-katex
Author-email: Fabian Braun <fsbraun@gmx.de>
License-Expression: MIT
License-File: LICENSE
Keywords: KaTeX,django CMS
Classifier: Development Status :: 5 - Production/Stable
Classifier: Environment :: Web Environment
Classifier: Framework :: Django
Classifier: Framework :: Django :: 4.2
Classifier: Framework :: Django :: 5.0
Classifier: Framework :: Django :: 5.1
Classifier: Framework :: Django :: 5.2
Classifier: Framework :: Django CMS :: 3.11
Classifier: Framework :: Django CMS :: 4.0
Classifier: Framework :: Django CMS :: 4.1
Classifier: Intended Audience :: Developers
Classifier: License :: OSI Approved :: MIT License
Classifier: Operating System :: OS Independent
Classifier: Programming Language :: Python
Classifier: Programming Language :: Python :: 3 :: Only
Classifier: Programming Language :: Python :: 3.9
Classifier: Programming Language :: Python :: 3.10
Classifier: Programming Language :: Python :: 3.11
Classifier: Programming Language :: Python :: 3.12
Classifier: Programming Language :: Python :: 3.13
Classifier: Programming Language :: Python :: 3.14
Classifier: Topic :: Internet :: WWW/HTTP :: Dynamic Content
Requires-Python: >=3.9
Requires-Dist: django-cms
Provides-Extra: static-ace
Requires-Dist: djangocms-static-ace; extra == 'static-ace'
